setup.py
bitraider/__init__.py
bitraider/example_strategy.py
bitraider/exchange.py
bitraider/strategy.py
bitraider/trader_template.py
bitraider.egg-info/PKG-INFO
bitraider.egg-info/SOURCES.txt
bitraider.egg-info/dependency_links.txt
bitraider.egg-info/entry_points.txt
bitraider.egg-info/not-zip-safe
bitraider.egg-info/requires.txt
bitraider.egg-info/top_level.txt