Metadata-Version: 1.0
Name: bitraider
Version: 0.0.4a0
Summary: A suite of tools for algorithmic Bitcoin trading
Home-page: http://github.com/ehickox2012/bitraider
Author: Eli Hickox
Author-email: ehicko2@illinois.edu
License: MIT
Platform: UNKNOWN
